<?xml version="1.0" encoding="UTF-8"?>
<xdbd_trigger_root
 xmlns:xsi='http://www.w3.org/2001/XMLSchema-instance'
 xsi:noNamespaceSchemaLocation='xdbd_trigger.xsd'>
 <xdbd_trigger>
  <trigger_id>1</trigger_id>
  <trigger_name>trigger_node</trigger_name>
  <trigger_library>libxdbdsdltrigger.so</trigger_library>
  <trigger_load>nmFunc_node_load</trigger_load>
  <trigger_fire>nmFunc_node_fire</trigger_fire>
  <trigger_unload>nmFunc_node_unload</trigger_unload>
  <trigger_table>node</trigger_table>
  <trigger_function>14</trigger_function>
 </xdbd_trigger>
 <xdbd_trigger>
  <trigger_id>2</trigger_id>
  <trigger_name>trigger_sys_interface</trigger_name>
  <trigger_library>libxdbdsdltrigger.so</trigger_library>
  <trigger_load>nmFunc_sys_interface_load</trigger_load>
  <trigger_fire>nmFunc_sys_interface_fire</trigger_fire>
  <trigger_unload>nmFunc_sys_interface_unload</trigger_unload>
  <trigger_table>sys_interface</trigger_table>
  <trigger_function>14</trigger_function>
 </xdbd_trigger>
 <xdbd_trigger>
  <trigger_id>3</trigger_id>
  <trigger_name>trigger_h248_nonstd_prf</trigger_name>
  <trigger_library>libxdbdsdltrigger.so</trigger_library>
  <trigger_load>nmFunc_h248_nonstd_prf_load</trigger_load>
  <trigger_fire>nmFunc_h248_nonstd_prf_fire</trigger_fire>
  <trigger_unload>nmFunc_h248_nonstd_prf_unload</trigger_unload>
  <trigger_table>h248_nonstd_prf</trigger_table>
  <trigger_function>14</trigger_function>
 </xdbd_trigger>
 <xdbd_trigger>
  <trigger_id>4</trigger_id>
  <trigger_name>trigger_vxml_trace</trigger_name>
  <trigger_library>libxdbdsdltrigger.so</trigger_library>
  <trigger_load>nmFunc_vxml_trace_load</trigger_load>
  <trigger_fire>nmFunc_vxml_trace_fire</trigger_fire>
  <trigger_unload>nmFunc_vxml_trace_unload</trigger_unload>
  <trigger_table>vxml_trace</trigger_table>
  <trigger_function>14</trigger_function>
 </xdbd_trigger>
 <xdbd_trigger>
  <trigger_id>5</trigger_id>
  <trigger_name>trigger_h248_intf_profile</trigger_name>
  <trigger_library>libxdbdsdltrigger.so</trigger_library>
  <trigger_load>nmFunc_h248_intf_profile_load</trigger_load>
  <trigger_fire>nmFunc_h248_intf_profile_fire</trigger_fire>
  <trigger_unload>nmFunc_h248_intf_profile_unload</trigger_unload>
  <trigger_table>h248_intf_profile</trigger_table>
  <trigger_function>14</trigger_function>
 </xdbd_trigger>
 <xdbd_trigger>
  <trigger_id>6</trigger_id>
  <trigger_name>trigger_statistics_group</trigger_name>
  <trigger_library>libxdbdsdltrigger.so</trigger_library>
  <trigger_load>nmFunc_statistics_group_load</trigger_load>
  <trigger_fire>nmFunc_statistics_group_fire</trigger_fire>
  <trigger_unload>nmFunc_statistics_group_unload</trigger_unload>
  <trigger_table>statistics_group</trigger_table>
  <trigger_function>14</trigger_function>
 </xdbd_trigger>
 <xdbd_trigger>
  <trigger_id>7</trigger_id>
  <trigger_name>trigger_vxml_config</trigger_name>
  <trigger_library>libxdbdsdltrigger.so</trigger_library>
  <trigger_load>nmFunc_vxml_config_load</trigger_load>
  <trigger_fire>nmFunc_vxml_config_fire</trigger_fire>
  <trigger_unload>nmFunc_vxml_config_unload</trigger_unload>
  <trigger_table>vxml_config</trigger_table>
  <trigger_function>14</trigger_function>
 </xdbd_trigger>
 <xdbd_trigger>
  <trigger_id>8</trigger_id>
  <trigger_name>trigger_vxml_server</trigger_name>
  <trigger_library>libxdbdsdltrigger.so</trigger_library>
  <trigger_load>nmFunc_vxml_server_load</trigger_load>
  <trigger_fire>nmFunc_vxml_server_fire</trigger_fire>
  <trigger_unload>nmFunc_vxml_server_unload</trigger_unload>
  <trigger_table>vxml_server</trigger_table>
  <trigger_function>14</trigger_function>
 </xdbd_trigger>
 <xdbd_trigger>
  <trigger_id>9</trigger_id>
  <trigger_name>trigger_media_options</trigger_name>
  <trigger_library>libxdbdsdltrigger.so</trigger_library>
  <trigger_load>nmFunc_media_options_load</trigger_load>
  <trigger_fire>nmFunc_media_options_fire</trigger_fire>
  <trigger_unload>nmFunc_media_options_unload</trigger_unload>
  <trigger_table>media_options</trigger_table>
  <trigger_function>14</trigger_function>
 </xdbd_trigger>
 <xdbd_trigger>
  <trigger_id>10</trigger_id>
  <trigger_name>trigger_gain_control_profile</trigger_name>
  <trigger_library>libxdbdsdltrigger.so</trigger_library>
  <trigger_load>nmFunc_gain_control_profile_load</trigger_load>
  <trigger_fire>nmFunc_gain_control_profile_fire</trigger_fire>
  <trigger_unload>nmFunc_gain_control_profile_unload</trigger_unload>
  <trigger_table>gain_control_profile</trigger_table>
  <trigger_function>14</trigger_function>
 </xdbd_trigger>
 <xdbd_trigger>
  <trigger_id>11</trigger_id>
  <trigger_name>trigger_h248_interface</trigger_name>
  <trigger_library>libxdbdsdltrigger.so</trigger_library>
  <trigger_load>nmFunc_h248_interface_load</trigger_load>
  <trigger_fire>nmFunc_h248_interface_fire</trigger_fire>
  <trigger_unload>nmFunc_h248_interface_unload</trigger_unload>
  <trigger_table>h248_interface</trigger_table>
  <trigger_function>14</trigger_function>
 </xdbd_trigger>
 <xdbd_trigger>
  <trigger_id>12</trigger_id>
  <trigger_name>trigger_h248_trace</trigger_name>
  <trigger_library>libxdbdsdltrigger.so</trigger_library>
  <trigger_load>nmFunc_h248_trace_load</trigger_load>
  <trigger_fire>nmFunc_h248_trace_fire</trigger_fire>
  <trigger_unload>nmFunc_h248_trace_unload</trigger_unload>
  <trigger_table>h248_trace</trigger_table>
  <trigger_function>14</trigger_function>
 </xdbd_trigger>
 <xdbd_trigger>
  <trigger_id>13</trigger_id>
  <trigger_name>trigger_ext_media_options</trigger_name>
  <trigger_library>libxdbdsdltrigger.so</trigger_library>
  <trigger_load>nmFunc_ext_media_options_load</trigger_load>
  <trigger_fire>nmFunc_ext_media_options_fire</trigger_fire>
  <trigger_unload>nmFunc_ext_media_options_unload</trigger_unload>
  <trigger_table>ext_media_options</trigger_table>
  <trigger_function>14</trigger_function>
 </xdbd_trigger>
 <xdbd_trigger>
  <trigger_id>14</trigger_id>
  <trigger_name>trigger_coco_net_addr</trigger_name>
  <trigger_library>libxdbdsdltrigger.so</trigger_library>
  <trigger_load>nmFunc_coco_net_addr_load</trigger_load>
  <trigger_fire>nmFunc_coco_net_addr_fire</trigger_fire>
  <trigger_unload>nmFunc_coco_net_addr_unload</trigger_unload>
  <trigger_table>coco_net_addr</trigger_table>
  <trigger_function>14</trigger_function>
 </xdbd_trigger>
 <xdbd_trigger>
  <trigger_id>15</trigger_id>
  <trigger_name>trigger_cas_reg_param</trigger_name>
  <trigger_library>libxdbdsdltrigger.so</trigger_library>
  <trigger_load>nmFunc_cas_reg_param_load</trigger_load>
  <trigger_fire>nmFunc_cas_reg_param_fire</trigger_fire>
  <trigger_unload>nmFunc_cas_reg_param_unload</trigger_unload>
  <trigger_table>cas_reg_param</trigger_table>
  <trigger_function>14</trigger_function>
 </xdbd_trigger>
 <xdbd_trigger>
  <trigger_id>16</trigger_id>
  <trigger_name>trigger_reg_sig_level</trigger_name>
  <trigger_library>libxdbdsdltrigger.so</trigger_library>
  <trigger_load>nmFunc_reg_sig_level_load</trigger_load>
  <trigger_fire>nmFunc_reg_sig_level_fire</trigger_fire>
  <trigger_unload>nmFunc_reg_sig_level_unload</trigger_unload>
  <trigger_table>reg_sig_level</trigger_table>
  <trigger_function>14</trigger_function>
 </xdbd_trigger>
 <xdbd_trigger>
  <trigger_id>17</trigger_id>
  <trigger_name>trigger_protocol_qos</trigger_name>
  <trigger_library>libxdbdsdltrigger.so</trigger_library>
  <trigger_load>nmFunc_protocol_qos_load</trigger_load>
  <trigger_fire>nmFunc_protocol_qos_fire</trigger_fire>
  <trigger_unload>nmFunc_protocol_qos_unload</trigger_unload>
  <trigger_table>protocol_qos</trigger_table>
  <trigger_function>14</trigger_function>
 </xdbd_trigger>
 <xdbd_trigger>
  <trigger_id>18</trigger_id>
  <trigger_name>trigger_node_config</trigger_name>
  <trigger_library>libxdbdsdltrigger.so</trigger_library>
  <trigger_load>nmFunc_node_config_load</trigger_load>
  <trigger_fire>nmFunc_node_config_fire</trigger_fire>
  <trigger_unload>nmFunc_node_config_unload</trigger_unload>
  <trigger_table>node_config</trigger_table>
  <trigger_function>14</trigger_function>
 </xdbd_trigger>
 <xdbd_trigger>
  <trigger_id>19</trigger_id>
  <trigger_name>trigger_mf_tone</trigger_name>
  <trigger_library>libxdbdsdltrigger.so</trigger_library>
  <trigger_load>nmFunc_mf_tone_load</trigger_load>
  <trigger_fire>nmFunc_mf_tone_fire</trigger_fire>
  <trigger_unload>nmFunc_mf_tone_unload</trigger_unload>
  <trigger_table>mf_tone</trigger_table>
  <trigger_function>14</trigger_function>
 </xdbd_trigger>
 <xdbd_trigger>
  <trigger_id>20</trigger_id>
  <trigger_name>trigger_media_opt_by_func</trigger_name>
  <trigger_library>libxdbdsdltrigger.so</trigger_library>
  <trigger_load>nmFunc_media_opt_by_func_load</trigger_load>
  <trigger_fire>nmFunc_media_opt_by_func_fire</trigger_fire>
  <trigger_unload>nmFunc_media_opt_by_func_unload</trigger_unload>
  <trigger_table>media_opt_by_func</trigger_table>
  <trigger_function>14</trigger_function>
 </xdbd_trigger>
 <xdbd_trigger>
  <trigger_id>21</trigger_id>
  <trigger_name>trigger_rtp_limit</trigger_name>
  <trigger_library>libxdbdsdltrigger.so</trigger_library>
  <trigger_load>nmFunc_rtp_limit_load</trigger_load>
  <trigger_fire>nmFunc_rtp_limit_fire</trigger_fire>
  <trigger_unload>nmFunc_rtp_limit_unload</trigger_unload>
  <trigger_table>rtp_limit</trigger_table>
  <trigger_function>14</trigger_function>
 </xdbd_trigger>
 <xdbd_trigger>
  <trigger_id>22</trigger_id>
  <trigger_name>trigger_rtp_control</trigger_name>
  <trigger_library>libxdbdsdltrigger.so</trigger_library>
  <trigger_load>nmFunc_rtp_control_load</trigger_load>
  <trigger_fire>nmFunc_rtp_control_fire</trigger_fire>
  <trigger_unload>nmFunc_rtp_control_unload</trigger_unload>
  <trigger_table>rtp_control</trigger_table>
  <trigger_function>14</trigger_function>
 </xdbd_trigger>
 <xdbd_trigger>
  <trigger_id>23</trigger_id>
  <trigger_name>trigger_rtp_quality</trigger_name>
  <trigger_library>libxdbdsdltrigger.so</trigger_library>
  <trigger_load>nmFunc_rtp_quality_load</trigger_load>
  <trigger_fire>nmFunc_rtp_quality_fire</trigger_fire>
  <trigger_unload>nmFunc_rtp_quality_unload</trigger_unload>
  <trigger_table>rtp_quality</trigger_table>
  <trigger_function>14</trigger_function>
 </xdbd_trigger>
</xdbd_trigger_root>
